setup.py
.github/workflows/main.yml
__pycache__/scraper.cpython-38.pyc
__pycache__/scraper.cpython-39.pyc
animal_scraper.egg-info/PKG-INFO
animal_scraper.egg-info/SOURCES.txt
animal_scraper.egg-info/dependency_links.txt
animal_scraper.egg-info/requires.txt
animal_scraper.egg-info/top_level.txt
scraper/__init__.py
scraper/animal_scraper.py
scraper/scraper.py
test/test_animal.py