Metadata-Version: 1.0
Name: animal-scraper
Version: 0.1.1
Summary: Mock package that downloads images of animals
Home-page: UNKNOWN
Author: Ivan Ying
Author-email: UNKNOWN
License: MIT
Platform: UNKNOWN
